willowtree/__init__.py
willowtree/celltree.py
willowtree/compare.py
willowtree/tree.py
willowtree-0.1.2.dist-info/LICENSE
willowtree-0.1.2.dist-info/METADATA
willowtree-0.1.2.dist-info/WHEEL
willowtree-0.1.2.dist-info/top_level.txt
willowtree-0.1.2.dist-info/RECORD
